package_dev_tools/__init__.py
package_dev_tools/py.typed
package_dev_tools/actions/__init__.py
package_dev_tools/actions/instantiate_new_project/__init__.py
package_dev_tools/actions/instantiate_new_project/cleanup_readme.py
package_dev_tools/actions/instantiate_new_project/cleanup_workflows.py
package_dev_tools/actions/instantiate_new_project/git.py
package_dev_tools/actions/instantiate_new_project/instantiate_new_project.py
package_dev_tools/actions/instantiate_new_project/substitute_template_name/__init__.py
package_dev_tools/actions/instantiate_new_project/substitute_template_name/project.py
package_dev_tools/actions/instantiate_new_project/substitute_template_name/substitute_template_name.py
package_dev_tools/actions/template_sync/__init__.py
package_dev_tools/actions/template_sync/git.py
package_dev_tools/actions/template_sync/merge.py
package_dev_tools/actions/template_sync/sync.py
package_dev_tools/actions/template_sync/trigger.py
package_dev_tools/cli/__init__.py
package_dev_tools/cli/check_coverage.py
package_dev_tools/cli/check_shields.py
package_dev_tools/cli/cleanup_readme.py
package_dev_tools/cli/export_pre_commit_config.py
package_dev_tools/cli/extract_package_name.py
package_dev_tools/cli/extract_required_python_version.py
package_dev_tools/cli/extract_supported_python_versions.py
package_dev_tools/cli/instantiate_new_project.py
package_dev_tools/cli/substitute_template_name.py
package_dev_tools/cli/sync_template.py
package_dev_tools/cli/trigger_template_sync.py
package_dev_tools/models/__init__.py
package_dev_tools/models/path.py
package_dev_tools/pre_commit/__init__.py
package_dev_tools/pre_commit/check_coverage.py
package_dev_tools/pre_commit/check_import.py
package_dev_tools/pre_commit/check_shields.py
package_dev_tools/pre_commit/export_config.py
package_dev_tools/utils/__init__.py
package_dev_tools/utils/badge.py
package_dev_tools/utils/package.py
package_dev_tools-0.7.1.data/scripts/bump-version
package_dev_tools-0.7.1.dist-info/licenses/LICENSE
package_dev_tools-0.7.1.dist-info/METADATA
package_dev_tools-0.7.1.dist-info/WHEEL
package_dev_tools-0.7.1.dist-info/entry_points.txt
package_dev_tools-0.7.1.dist-info/top_level.txt
package_dev_tools-0.7.1.dist-info/RECORD
