Metadata-Version: 2.4
Name: package-dev-tools
Version: 0.7.1
Summary: CI/CD tools for Python packages
Author-email: Quinten Roets <qdr2104@columbia.edu>
License-Expression: MIT
Project-URL: Source Code, https://github.com/quintenroets/package-dev-tools
Requires-Python: >=3.10
License-File: LICENSE
Requires-Dist: package-utils<1,>=0.6.1
Requires-Dist: powercli<1,>=0.1.2
Requires-Dist: pygithub<3,>=2.1.1
Requires-Dist: python-slugify<9,>=8.0.1
Requires-Dist: simple-classproperty<5,>=4.0.2
Requires-Dist: superpathlib<3,>=2.0.0
Requires-Dist: toml<1,>=0.10.2
Requires-Dist: autotyping<25,>=23.3.0
Requires-Dist: bump2version<2,>=1.0.1
Requires-Dist: coverage<8,>=7.4.0
Requires-Dist: libcst<2,>=1.7.0
Requires-Dist: pre-commit<5,>=3.5.0
Requires-Dist: pytest<9,>=7.4.3
Requires-Dist: docformatter<1.8,>=1.7.5
Requires-Dist: mypy<1.16,>=1.15.0
Requires-Dist: ruff<0.12,>=0.11.8
Provides-Extra: dev
Requires-Dist: hypothesis<7,>=6.91.0; extra == "dev"
Requires-Dist: package-dev-utils<1,>=0.1.6; extra == "dev"
Requires-Dist: types-requests<3,>=2.31.0.10; extra == "dev"
Requires-Dist: types-toml<1,>=0.10.8.7; extra == "dev"
Dynamic: license-file
